{
  "chapter_number": 107,
  "chapter_title": "About Gathering many People for Food",
  "book_number": 1,
  "hadith_entries": [
    {
      "hadith_number": 366,
      "narrator": "Abu-Huraira",
      "text": "366. Narrated Abu-Huraira : 'Allah's Messenger\nsaid: \"The food for two people is sufficient for three, and the\nfood of three people is sufficient for four people.\" (Bukhari)",
      "source_collection": "Bukhari",
      "char_count": 173
    }
  ],
  "quran_refs": [],
  "total_hadith": 1,
  "total_chars": 224
}