{
  "chapter_number": 141,
  "chapter_title": "About Reminding a Dying Person of Al-Shahada",
  "book_number": 1,
  "hadith_entries": [
    {
      "hadith_number": 471,
      "narrator": "Abu-Sa'eed",
      "text": "471. Narrated Abu-Sa'eed and Abu-Huraira: 'Allah's\nMessenger said: \"Let those of you who are dying repeat\nafter you: \"There is no God but Allah.\" (Muslim)",
      "source_collection": "Muslim",
      "char_count": 154
    }
  ],
  "quran_refs": [],
  "total_hadith": 1,
  "total_chars": 241
}