{
  "id": "thematic_003",
  "surah_number": 3,
  "surah_name": "Al Imran",
  "surah_name_transliterated": "®l ¢Imr¥n",
  "surah_name_english": "House of ¢Imr¥n",
  "page_start": 30,
  "page_end": 54,
  "synopsis": "it is easy to identify immediately the subject matter of this\nsurah. It revolves around two major issues: the debate with the\nPeople of the Book, the Jews and the Christians, of whom the Jews\nwere Madinah natives incited to oppose Islam; and a review and\nassessment of the humiliating and tragic defeat suffered by the\nMuslims at the battle of U^ud in 625 ac.",
  "sections": [
    {
      "section_index": 0,
      "text": "it is easy to identify immediately the subject matter of this\nsurah. It revolves around two major issues: the debate with the\nPeople of the Book, the Jews and the Christians, of whom the Jews\nwere Madinah natives incited to oppose Islam; and a review and\nassessment of the humiliating and tragic defeat suffered by the\nMuslims at the battle of U^ud in 625 ac. The two issues are treated\nseparately to begin with, but halfway through the surah they are\nbrought together and from then on are discussed as almost one sub-\nject. The outcome of the whole discussion seems to focus on the fact\nthat perseverance and steadfastness are required to face both issues:\nthe scheming of the Jewish establishment inside Madinah and the\nattacks by the inﬁdels from outside it.\n    Islam is a religion addressed to all human societies without coer-\ncion or discrimination. Whoever responds positively is taken into\nthe fold, while those who turn away are left in peace. However—as\nmentioned earlier—those who commit aggression against Islam and\nthe Muslims are boldly confronted. This is clear from the verse:\n   If they argue with you, say: “I have surrendered myself to God and\n   so have those who followed me.” As for those who had received the\n   scriptures and the illiterates [pagan Arabs with no revealed scrip-\n   tures], ask them: “Have you surrendered yourselves to God?” If\n   they have they shall be rightly guided; but if they turn away, then\n   your only duty is to deliver the message to them. God is watching\n   His servants. (20)\n\n   The surah begins by stressing that Islam is a universal guidance,\nand the Qur’an a conﬁrmation of all previous revelation. God’s rev-\nelation is one, in the sense that it sets the truth apart from falsehood\nin a sharp and unequivocal manner. The surah highlights the fact\nthat Moses, Jesus and Muhammad have trodden the same path, and\nthat the scope of Islam encompasses all other revealed religions\nregardless of their time and place. The Torah and the Gospel are\nboth referred to here as “God’s revelation [or messages].” This\nphrase occurs ten times in the surah, as in verse 4 which says: “Those\nwho deny God’s revelations [messages], grievous suffering awaits\nthem; for God is Mighty and capable of retribution,” and verse 199,\ntowards the end of the surah:\n\n   There are among the People of the Book [Jews and Christians]\n   those who believe in God and what has been revealed to you and to\n   them. They humble themselves before God and do not exchange\n   God’s revelations [messages] for a triﬂing price.\n\n    There could be no contradiction nor differences in the basic\ntenets and principles of divine faith, nor in what was revealed to\nMuhammad and his earlier brothers in the line of prophets, Moses\nand Jesus. Contradictions can exist only between God’s revelation\nand the false notions and philosophies that people put forward.\nBelief, as presented in the Qur’an, applies to what has been revealed\nto the Muslims and to those before them. Those who deviate from it\nought to repent and return to the straight path. The “People of the\nBook” is a term that refers to Jews and Christians. Unlike the debate\nwith the Jews, that with the Christians in Madinah was calm and\nunhurried. The Jews had their own settlements inside Madinah itself\nand in other parts of northern Hijaz. Their elders resisted Islam,\ngainsaid God’s revelations and berated His Messenger. Moreover,\nthey collaborated with the pagan Arabs in their insidious efforts and\nﬁghts against Islam and the Muslims. They were encouraged by\n\n\f               A Thematic Commentary on the Qur’an\n\ntheir wealth and economic power and the strong foothold they had\nsecured in Madinah. This was repeatedly condemned in the surah\n(10, 21, 116, 196, 197), for excessive wealth and afﬂuence would\nlead individuals as well as nations to ignore God and overreach\nthemselves in pursuit of power and inﬂuence.\n   Although the Jewish settlements in Hijaz were much more\ndeveloped and economically prosperous than other cities and towns\nin Arabia, they had never used any of their wealth or expertise for\nthe development and welfare of the region as a whole. With its well-\nestablished traditions of self-dignity, honesty, and hospitality, the\npagan Arab society could, in fact, be said to have been more liberal\nand charitable than other communities in their midst. When\nProphet Muhammad began to spread his teachings, he proved to\nbe more persuasive and endearing, and less condescending, than the\nJewish spokesmen who had been exposed as arrogant and self-cen-\ntered. Their attitudes and conduct had in the end led to their defeat\nand the end of their inﬂuence and existence in the area.\n   The Jews had enjoyed the honor and privilege of custodianship\nof God’s revelation for several successive generations. They had\nbeen entrusted with it for so long that they had come to nurture\nthe false belief that God’s revelation belonged to them and to\nthem alone—a nation that would have the eternal indisputable\nright to hold and interpret God’s revelations and reap their beneﬁt\nfor ever. They were hopelessly mistaken. Honor, privilege, status,\nand leadership in the world have to be earned through devotion\nand hard work.\n   By the time Prophet Muhammad had emerged, the Jews’ capaci-\nty to carry God’s revelation forward had reached its nadir. Their\nrabbis’ hearts had turned hard, morals had deteriorated, and\nselﬁshness had gained the upper hand; greed for material and world-\nly possessions and privileges had become their sole preoccupation.\nWorse than that, they had also displayed signs of insolence and\ninsubordination towards and rejection of God and the mission with\n\nwhich He had entrusted their race. And so it was necessary to trans-\nfer the responsibility and the trust to another human group, which\nwas better qualiﬁed and which would give it the effort and devotion\nit deserved. The surah expresses this in the following verse:\n\n   Say, “Lord, Sovereign of all creation, You bestow sovereignty on\n   whom You will and take away from whom You will. You raise\n   whomever You will and abase whomever You will. All Goodness\n   lies in Your hands. You have power over all things.” (26)\n\nThis fundamental assertion is preceded by elaborate reasons and\nconsiderations such as:\n\n   Have you not taken note of those who received portions of the\n   Book [revelation]? When they are called upon to accept the judg-\n   ment of God’s Book, some of them turn away and take no heed. It\n   is because they said, “We shall suffer the ﬁre for a few days only.”\n   (23–24)\n\nThey were so overcome by that false sense of security that they\nturned to open rebellion, squandering the divine injunctions and\nreneging on their commitment to them.\n    God’s response to that was to conﬁrm divine justice towards all\npeople and to dispel the erroneous idea that God was biased towards\nany particular ethnic or racial group, saying: “What will they do\nwhen We gather them all together upon a day that is sure to come,\nwhen every soul will be given what it earned with no injustice\nwhatsoever?” (25). In God’s eyes, people are all equal; each shall\nreap his or her just rewards according to their behavior and conduct.\nWhen humankind is brought before God for judgment, each\nhuman being shall face the Creator alone. The one thing that would\nredeem any of them shall be their piety, and the depth and sincerity\nof their belief in God.\n\n\f               A Thematic Commentary on the Qur’an\n\n    It is important to keep in mind that although those words are\naddressed to Jews in Arabia, they also serve as a subtle reminder to\nother human groups. God was not going to chastise the Jews for\ntheir deviation, and overlook the misdemeanor of the Arabs if they\nwere to follow their example. Similar actions and activities would\nearn similar reactions and responses. The pitfall in which errant Jews\nwere caught was their misconception that the Torah had been\ngraced by them rather than the other way around, and this had led to\ntheir fateful fall from God’s grace and favor. Today, there are Arabs\nwho refuse to be associated with Islam and try to separate it from\nArab culture and history. Their fate could not be any different from\nthat of the misguided Jews of Madinah before them. God does not\nmake any undue or unmerited preferences among humans.\n    The debate with the People of the Book is covered over a large\npart of this surah, and apart from a ﬂeeting allusion in verse 6 to the\nbirth of Jesus, was mainly directed at the Jews of Arabia whose ani-\nmosity towards the early Muslims was much more pronounced. In\nsaying: “It is He who creates you as He pleases inside the mothers’\nwombs; there is no god but Him, the Mighty, the Wise,” the surah\noutlines God’s stupendous power to create human beings and shape\ntheir form, soul, and body, and in the same breath alludes to the fact\nthat Jesus’ miraculous birth was but one of a multitude of feats and\nincredible acts of God. He has shown humankind veritable signs of\nsuperiority and ingenuity in His creation, endowing some people\nwith higher qualities and aptitudes than others. Jesus’ fatherless\nconception and birth were but two of these extraordinary and\nexceptional acts. This is a subject which we shall come to discuss\nlater.",
      "verse_refs": [
        {
          "type": "same_surah",
          "verse": "20"
        },
        {
          "type": "same_surah",
          "verse": "26"
        },
        {
          "type": "same_surah",
          "verse": "25"
        },
        {
          "type": "same_surah",
          "verse": "23-24"
        }
      ],
      "char_count": 9263
    },
    {
      "section_index": 1,
      "text": "As to the hostility exhibited towards the Muslims by the Jewish\nestablishment in Madinah, its main underlying reason was the\n\ntransfer of prophethood from their patriarchs to Muhammad. That\nprophethood had given them such a special and unique status over\nall the rest of humankind, and seeing it being taken away from them\nand entrusted to the Arabs enraged them and ﬁred up their fury and\nhatred towards them. Their reaction was severely and immediately\ncondemned in the Qur’an: “People of the Book! Why do you deny\nGod’s revelations when you are witnesses to their veracity? Why do\nyou confound the true with the false and hide the truth knowingly?”\n(70–71). It is clear from the tone of this reprimand that the Jewish\npriests and elders were aware that Muhammad was genuine in his\nclaim of relaying God’s words and being His spokesman. It is also\nimplicit in the address that they were guilty of transgression against\nGod, that they rejected a reconciliation with Him, that they persist-\ned with their refusal to acknowledge Muhammad’s prophethood,\nand went on to oppose and resist it with arms, seditious scheming,\nand active collaboration with his other enemies, the pagan Arabs.\nThe reproach is repeated several times in the surah: “How would\nGod guide people who rejected the faith after believing in it and\nhaving borne witness that the Messenger is true and after receiving\nveritable signs!” (86). Elsewhere God’s Messenger is directed to ask\nthem, saying:\n\n   “People of the Book, why do you deny God’s revelations, when\n   God is witness to what you do?” Say, “People of the Book, why do\n   you drive believers away from God’s path, seeking to mislead and\n   confuse, when you yourselves are witnesses? God is not unaware of\n   what you do.” (98–99)\n\n    To countermand this criticism, some Jews came up with the bril-\nliant stratagem of feigning their acceptance of Islam in order to\nconceal their antagonism and prove their tolerance and fair-mind-\nedness towards the new religion. The logic of their argument would\nlead them to say that their rejection of, and opposition to Islam had\n\n\f               A Thematic Commentary on the Qur’an\n\ncome as a result of direct ﬁrsthand experience of it. The surah says:\n“Some of the People of the Book said [to one another], ‘Believe in\nthat which is revealed to the faithful in the morning and abandon it\nin the evening, so that they may themselves go back on their faith’”\n(72). The surah also exposes this group’s determined rejection of the\nnew revelation and their dogged resentment of the transfer of divine\ntrust away from the Hebrews, by reporting their statement: “Believe\nin none except those who follow your own religion” (73). The\ninference here is that they ﬁrmly believed in the superiority of their\nreligion over all others.\n    So it was clear that the rabbis were not happy with God’s decision\nto give preference to the Arabs and choose them this time round to\nbe the custodians of His revelation. If they only could, they would\nforce God to go back on that choice and change the course of\nhistory by restoring the leadership of humankind to them. God’s\nresponse was clear and decisive: “Grace is in the hand of God; He\nbestows it on whom He will. God is Muniﬁcent and All-Knowing.\nHe favors with His mercy whom He will. His grace is immense”\n(73–74). However, the group had acquired several vices, not least\ntheir self-importance, hard-headedness, and conceit, that could at\ntimes of weakness turn into deep-seated hatred and, at times of pros-\nperity and triumph, into open hostility and belligerence. These\ncharacteristics seem to have colored much rabbinical writing, driv-\ning the Jewish people into isolation and making them tragically\nvulnerable to persecution by other societies and groups. The surah\noffers the explanation that “they [the Jewish elders] say, ‘We are not\nbound to keep faith with the unlettered [the Gentiles].’ They know-\ningly tell lies about God” (75). The Arabic term ummiyÏn used in\nthis verse literally means “unlettered,” but could also mean “non-\nJews” or Gentiles (Hebrew: Goyim). In the one case it would be a\nreference to the Arabs, while in the other it would be a reference\nto non-Jewish communities in general. Jewish religious script-\nures, especially the Torah and the Talmud, as well as parts of their\n\nliterature, do advocate the idea of the superiority of the Jewish\nnation over other nations, and propound the concept of Jews as the\n‘chosen people of God.’ The Qur’an explains very clearly that the\nrelationship between God and humans cannot be based on false\nclaims, but rather on sound ethical grounds, and on faith and trust.\nIn it we read: “Indeed, for those who keep their covenant and fear\nGod, God loves the righteous” (76).\n    At this point in the surah we may inquire why the subject of the\npilgrimage is suddenly brought up for discussion halfway through it,\nhaving covered the debates with the People of the Book and their\nbehavior. Indeed, we may even ask why the subject of permitted\nand forbidden foods is raised here also. After a great deal of reﬂec-\ntion, and with reference to Shaykh Muhammad RashÏd Ri\\¥’s\ncommentary in al-Man¥r, I was able to ﬁnd the answer. As Islam was\nbeing introduced to the Jews, they questioned the idea of adopting a\nreligion which allowed them to eat certain foods that their own reli-\ngion had forbidden them. The answer they were given was that the\nembargo imposed on them regarding the consumption of certain\nfoods had been temporary, and had come about as punishment for\nearlier intransigence and insubordination to God’s commands. This\nis covered more fully in surah al-An¢¥m where it is stated:\n\n   Such is the penalty We imposed on them for their misdeeds. What\n   We declare is true. If they do not believe you say, “Your Lord’s\n   mercy is vast, but His punishment cannot be averted by the trans-\n   gressors.” (al-An¢¥m: 146–47)\n\nJesus, as we know, sought to relieve the Jews of some of the burdens\nplaced upon them. This is given in verse 50 of this surah, which\nquotes Jesus as saying to the Jews: “‘I come to conﬁrm the Torah\nalready revealed and to make lawful to you some of what was for-\nbidden you.’” The Qur’an restored the divine law to its original\nform, forbidding only certain types of carrion meat, swine ﬂesh, spilt\n\n\f                A Thematic Commentary on the Qur’an\n\nblood, and the meat of animals slaughtered without invoking God’s\nname—all other types of food would be permissible. Verse 93 of the\nsurah says: “All food was lawful to the Israelites except what Israel\n[Jacob] forbade himself before the Torah was revealed.”\n    The same argument applies in the case of the qiblah, or the direc-\ntion faced by Muslims during salah. As verse 96 afﬁrms, the Ka¢bah\nat Makkah was the ﬁrst and only qiblah for all humankind. And\nalthough Jerusalem, for certain temporary reasons, had been chosen\nas the qibla for worshipers of God, those reasons no longer applied\nand the Ka¢bah was reinstated as the legitimate qiblah for all believers.\n    Putting differences between various religions and human ideolo-\ngies aside, the fact remains that sound moral and ethical discipline\nand education have proved to be the basis for human progress at all\nphases of human history. We ﬁnd reference to this very early in the\nsurah where God says:\n\n   Men are tempted by the allure of women and offspring, of hoarded\n   treasures of gold and silver, of splendid horses, cattle and vast planta-\n   tions. These are the comforts of this life, but to God is the best\n   return. (14)\n\nTrue, for human life to continue, the satisfaction and pursuance of\nthese desires is necessary. Without the sexual relationship between\nmen and women, human existence would have ceased long ago.\nThe same can be said of all other human desires. The crucial point\nhere is that they should be pursued in moderation, with discipline,\nand within a framework of reason and common sense. Islam has per-\nmitted all that is good and useful to people, and forbidden what is\nharmful. Islamic laws and teachings are built on the foundation of\nfaith in God and positive action, and they have provided for a great\ndeal that would nurture people’s relationship with God and main-\ntain their awareness of the hereafter.\n    We are used nowadays to hearing national leaders warning their\n\ncitizens against the AIDS virus and advising them to take certain\nprecautions during illicit sexual acts. They no longer call for proper\nlawful sexual relationships between people because they no longer\nbelieve that these are possible. This is only true in a society that has\nlost its faith and trust in God. Followers of formal religion shall con-\ntinue to suffer from their uncontrollable desires, unless they heed the\nwords of God, especially when He says:\n\n   Say, “Shall I tell of better things than these? For the righteous their\n   Lord has gardens beneath which rivers ﬂow, where they shall dwell\n   forever, spouses of high purity and God’s grace.” God is aware of\n   His servants, those who say: “Our Lord, we believed in You, so for-\n   give us our sins and save us the torment of the hellﬁre,” those who\n   are steadfast, sincere, devout, charitable and who pray for forgive-\n   ness during the small hours of the night. (15–17)\n\n   So we ﬁnd the surah opening with a statement addressed to the\nPeople of the Book that salvation could come only with a faith based\non the belief in “God, there is no god but Him, the Living, the\nEver-Existing one” (2), and in a way of life that acknowledges\nhuman nature within a discipline of decency and virtue that discou-\nrages all forms of excessive deprivation or overindulgence; a dis-\ncipline that renders enlightened life in this world a natural and\nmeaningful prelude to the life that is to come.",
      "verse_refs": [
        {
          "type": "same_surah",
          "verse": "86"
        },
        {
          "type": "same_surah",
          "verse": "72"
        },
        {
          "type": "same_surah",
          "verse": "73"
        },
        {
          "type": "same_surah",
          "verse": "75"
        },
        {
          "type": "same_surah",
          "verse": "76"
        },
        {
          "type": "same_surah",
          "verse": "14"
        },
        {
          "type": "same_surah",
          "verse": "2"
        },
        {
          "type": "same_surah",
          "verse": "70-71"
        },
        {
          "type": "same_surah",
          "verse": "98-99"
        },
        {
          "type": "same_surah",
          "verse": "73-74"
        },
        {
          "type": "same_surah",
          "verse": "15-17"
        },
        {
          "type": "cross_surah",
          "surah_name": "al-An¢¥m",
          "verse": "146–47"
        }
      ],
      "char_count": 9775
    },
    {
      "section_index": 2,
      "text": "Mary was a virgin throughout her pregnancy, having miraculously\nconceived Jesus. When some people began saying that Jesus was the\nson of God, it was clear that a groundless myth, a fallacy, was being\ncreated, pointing towards the existence of a special and intimate\nrelationship between God and Mary, the outcome of which was\nJesus. This outrageous notion reﬂects a deep-seated ignorance of\n\n\f               A Thematic Commentary on the Qur’an\n\nthe nature and status of God and the exaltation and gloriﬁcation that\nhumans owe Him. Surely, God could not be conceived of as an\nagent of reproduction in such a crude and salacious manner, for as\nGod says in the Qur’an: “Were God to have offspring, He would\nhave chosen the best of His creatures at will; Gloriﬁed is God, the\nOne, the Almighty” (al-Zumar: 4). It is true that Jesus’ conception\nand birth were abnormal and extraordinary events. Such was the\nwill and wisdom of God in order to show humankind that God is\nnot bound by the natural laws of causality, but rather He overrides\nand controls these laws. The story of Jesus and his mother is related\nfollowing that of Zachariah and his wife, which had also entailed\ncertain miraculous aspects.\n    Mary’s own conception and birth were unexpected by her\nmother. As soon as she knew that she was pregnant, she dedicated\nher baby to serving the temple in Jerusalem, and to worshiping and\nbeing devoted to the service of other worshipers. The Qur’an quotes\nher as saying: “‘Lord, I completely dedicate to Your service that\nwhich is in my womb. Accept it from me; You are All-Hearing, All-\nKnowing’” (35). However, contrary to her expectation, the baby\nturned out to be a girl and would not, therefore, be of much use in\nfulﬁlling that task which required men of strength and endurance. In\nthe circumstances, the son she was hoping to have would have given\nmore happiness than a daughter who would herself probably need\ncare and looking after. Naturally, the mother was not to know that\nher newly born daughter was destined to be the mother of a highly\nregarded and noble human being and would have the privilege of\nnursing him in his infancy, just as Moses and Muhammad were\nnursed by their respective mothers. It is interesting to note in passing\nthat these three great senior prophets had been respectively reared by\nmothers of humble means and status who had to seek and depend on\nGod’s help alone. History is witness here as elsewhere that women\ntoo can reach great heights in society with their nobility, magnani-\nmity, and strong belief. Mary’s mother prayed to her Lord saying:\n\n   “Lord, I have given birth to a daughter”—and God knows well of\n   what she was delivered, and that a male is not like a female,—“and I\n   have named her Mary. I seek Your protection for her and her off-\n   spring against Satan, the accursed one.” Her Lord graciously\n   accepted her and made her grow up a goodly child. (36–37)\n\nMary was brought up by Zachariah, an old and frail man, and his as\nyet childless wife. Zachariah was himself melancholy and heartbro-\nken for not having children of his own to inherit the leadership of\nthe Israelites in whom he had little faith, but for whose future he was\nconcerned. Despite his frailty, though, Zachariah struggled and per-\nsevered in bringing up the new addition to his family. However,\nZachariah began to notice some unusually fortunate developments\ntaking place within his household and certain provisions coming to\nthe possession of the new girl, and so he asked her: “Mary, how did\nyou come by this food?” She replied, “It is from God, who gives to\nwhom He wills without stint” (37).\n   This inﬂamed Zachariah’s heart with love for, and devotion to,\nGod. He began to look up to God for more extraordinary acts and\nfor such favors to be bestowed on him personally. He knew that\nGod could make a hitherto infertile female conceive and have chil-\ndren and give an elderly man the virility to produce offspring, and so\nhe prayed to God, saying:\n\n   “Lord, grant me goodly offspring, You hear all prayers.” The angels\n   called out to him while he was praying in the shrine, “God bids you\n   rejoice in the birth of John, who shall conﬁrm the word of God.”\n   (38-39)\n\nLife had returned to the despairing old couple; the barren wife\nwould be made to conceive by her elderly and infertile husband.\nThis only goes to show that when God wills, all the laws of nature\nsuccumb to His will. He can create and cause things to happen com-\npletely at will.\n\n\f                A Thematic Commentary on the Qur’an\n\n   Mary grew up in that—by then—happy, pious, and blessed\nhousehold, where God’s angels would be no strangers. They called\non Mary with more good news:\n\n   The angels said to Mary, “God gives you glad tidings of a word\n   from Him, whose name is the Messiah, Jesus the son of Mary. He\n   shall be noble in this world and in the hereafter, and shall be favored\n   by God. He shall talk to people in his cradle and in his adulthood,\n   and shall lead a righteous life.” She said, “Lord, how can I have a\n   child when no man has touched me?” He replied, “Such is the will\n   of God who creates whom He will. Once He decides on a matter,\n   He says, ‘Be’ and it is.” (45–47)\n\nThus Mary found herself on the threshold of a new and overwhelm-\ning experience, which a virgin girl would naturally undergo with\nextreme apprehension and trepidation. At one point she wished she\nwere dead. Nevertheless, the will of God was declared and Jesus was\nborn in that astounding and extraordinary way. Jesus was then\ncharged with the mission to address the Israelites with the message of\nGod in order to reform their state of affairs, break the arrogance of\ntheir chiefs, and commit them to a humble attitude towards God\nand their fellow humans.\n   Mary’s family was highly respected and venerated by people, and\nher son was held in high esteem by those who recognized the bless-\nings that accompanied his coming. However, there were Israelites\nwho took a different stand towards him. The Pharisees and skeptics\nrejected the miracles Jesus performed and refused to recognize him\nas an apostle of God. Furthermore, they claimed that his birth was\nno act of God, but the outcome of an illicit relationship between\nMary and a suitor of hers named Joseph the carpenter. Thus they\ncompounded their disbelief with slander. Jesus sought the support\nand the backing of reasonable and fair-minded people, some of\nwhom rallied around him and offered their backing, saying: “Lord,\n\nwe have believed in what You have sent down and have followed\nthe messenger, so please enlist us among the witnesses [to the truth]”\n(53). The Pharisees, however, went on with their intrigues against\nJesus and his followers even after, having delivered his Lord’s mes-\nsage, Jesus had passed away and was saved from their treachery and\nvicious scheming.\n    Although a large number of scholars believe that Jesus was raised\nto heaven alive, I ﬁnd myself more in agreement with those scholars\nwho say that he died a natural normal death. This would not dis-\ncount the idea, as the scholar Ibn ¤azm says, that he could have\nbeen brought back to normal life again to pursue his mission of\nspreading the creed of monotheism. Jesus’ story could, in this con-\ntext, be compared to that of the man who passed by a town which\nhad been destroyed, and inquired: “‘How can God bring life back to\nthis town, now that it is dead?’ Thereupon, God caused him to die,\nand after one hundred years brought him back to life” (al-Baqarah:\n259). It also can be compared to the story of the People of the Cave,\nwho remained dead for a few hundred years and then were brought\nback to life. The matter is very simple and the dispute is ﬁckle. Jesus\nmust be perceived as an ordinary human being, not as a god or a son\nof God.\n    The surah recalls the visit to Madinah by a Christian delegation\nwho went to debate with Prophet Muhammad aspects of the new\nreligion he was advocating. They argued that Jesus was human in\nform, only asking, of course, that if he were human, who was his\nfather? The Prophet replied that the absence of a human father did\nnot necessarily mean Jesus was the son of God. Based on their rea-\nsoning, Adam, who had neither father nor mother, would have\nbeen more eligible to divine parentage. We read in the surah that:\n“Jesus is like Adam in the sight of God. He created him of dust and\nthen said to him, ‘Be’ and he was. Truth comes from your Lord;\ndo not ever doubt it” (59–60). Nevertheless, the quibblers insisted\non their viewpoint and defended it with vehemence. The Prophet\n\n\f                A Thematic Commentary on the Qur’an\n\nthen proposed that the two camps, Christians and Muslims, should\nunite in prayer to God to curse the liars of either side. The surah\ncontinues:\n\n   Whoever disputes with you concerning Jesus after all the know-\n   ledge you have received, say to them, “Come, let us call out our\n   sons and your sons, our women and your women, ourselves and\n   yourselves, and then let us all jointly and earnestly pray that God’s\n   curse should fall upon the liars.” This is the true version [of events].\n   There is no god but God; He is Mighty and Wise. (61–62)\n\nThe Christian delegation refused to take part in that joint prayer to\nestablish the truth regarding the nature and status of Jesus, and up to\nthis day the two religions have continued to exist apart from one\nanother. It seems that the matter shall be settled only by Jesus himself\non his second coming to earth. He might be the one who will point\nout the liars and conﬁrm that the world knows only one overpower-\ning and almighty Master.",
      "verse_refs": [
        {
          "type": "same_surah",
          "verse": "35"
        },
        {
          "type": "same_surah",
          "verse": "37"
        },
        {
          "type": "same_surah",
          "verse": "53"
        },
        {
          "type": "same_surah",
          "verse": "36-37"
        },
        {
          "type": "same_surah",
          "verse": "38-39"
        },
        {
          "type": "same_surah",
          "verse": "45-47"
        },
        {
          "type": "same_surah",
          "verse": "59-60"
        },
        {
          "type": "same_surah",
          "verse": "61-62"
        },
        {
          "type": "cross_surah",
          "surah_name": "al-Zumar",
          "verse": "4"
        },
        {
          "type": "cross_surah",
          "surah_name": "al-Baqarah",
          "verse": "259"
        }
      ],
      "char_count": 9617
    },
    {
      "section_index": 3,
      "text": "Before closing the chapter on the People of the Book, the surah\ngives a critical account of the battle of U^ud, at which the Muslims\nof Madinah sustained a humiliating defeat at the hands of the pagan\nArabs in 625 ac. These were the original enemies of the early\nMuslims, who had no alternative but to face them and, as has been\nthe case ever since, ﬁght on two fronts simultaneously. The story\nbegins with verse 121 referring to the Prophet’s preparation for bat-\ntle, and then it suddenly breaks into a discussion of usury, spending,\nand the urgent need for repentance. Having covered these topics,\nthe surah picks up the account of the battle of U^ud again, which\ntakes us right to the end of the surah.\n    This leads us to look for a reason for this brief, but intriguing,\n\ndigression. The explanation seems to lie in the need for a cleansing, a\nreview, of the Muslim internal condition; to purge it of all signs of\nweakness and corruption in order to qualify the Muslims for victory\nin the battleﬁeld. ﬁghts such as the ones the Muslims were engaged\nin were not personal or nationalistic wars, but wars for values and\nprinciples. This is made very clear in the surah when it says: “It is of\nno concern of yours [Muhammad] when He [God] should forgive\nor punish them. They are transgressors” (128). Reconciliation or\nantipathy should be perpetrated for the sake of God only; for today’s\nenemies could very well be the allies of tomorrow, if they recon-\ncile their situation with God and submit to His will and teachings.\nUnder Islam, there is no room for private grudges or personal\nanimosity.\n    The defeat at U^ud contained a sharp lesson for the Muslims.\nTheir earlier triumph at Badr in 624 ac had opened the door for\nopportunists and those with special interests to join the growing\nMuslim community which showed clear promise of dominating the\nregion. One such prominent personality, ¢Abd Allah ibn Ubayy,\nsaw it coming and recognized the victory at Badr as setting an irre-\nversible trend that would result in the dominance of Islam. He\ndecided to convert and take all his followers with him. The surah\ncomments on this by saying: “God would not leave the believers in\ntheir current plight, without separating the bad from the good; nor\nwas God to let you in on the unknown” (179). The scene was then\nset for a setback, a test, that would distinguish those who were sin-\ncerely upholding Islam and supporting the Prophet and the Muslims\nthrough thick and thin from those who were in it merely for per-\nsonal gain or prestige.\n    Under such circumstances, one can normally distinguish two\nmain groups of people: those who are sincere and dedicated to the\ncommon cause, no matter what happens; and those whose main\nconcern is their own safety and self-interest, who hold little faith in\nGod or their fellow human beings. The surah describes these by\n\n\f                A Thematic Commentary on the Qur’an\n\nsaying: “And a group who were only concerned about themselves,\ndoubting God in their ignorant ways. They ask, ‘Do we stand to\ngain anything?’” (154). The latter group are always disgruntled and\nrestless, because their views are rarely given credence and they are\nseldom, if ever, accorded respect or prominence. Any society, and\nfar more an army, would be wiser to be rid of such people.\n    Contrary to the opinion of some, the Muslims’ defeat at U^ud\ndid not come as a result of bad planning or faulty tactics. It was the\nresult of insubordination, for some Muslim ﬁghters, at a very critical\npoint during the battle, neglected their duties by abandoning their\nbattle positions in pursuit of the loot. Had those ﬁghters adhered to\ntheir orders as given by the Prophet, the outcome would have been\ntotally different. The surah recalls:\n\n   God fulﬁlled His pledge to you when, by His leave, you trounced\n   them [the unbelievers at U^ud], until the moment when you lost\n   heart, started squabbling among yourselves and disobeyed the\n   Messenger just as you were close to victory. Some of you chose the\n   gains of this world, but others chose the rewards of the life to come.\n   (152)\n\nThe Muslims’ attitude in the battleﬁeld had changed and therefore\nthe outcome had also to change. “He [God] prevented you from\ndefeating them in order to test you. But now He has forgiven you,\nfor He is gracious to the believers” (152).\n   The defeat came as a shock to the Muslims and they were shaken\nby it. They questioned how and why it could have happened at all,\nand God’s answer was:\n\n   Now that a disaster has befallen you, after you yourselves have\n   inﬂicted [on your enemies] losses twice as heavy, you come to ask,\n   “How could this have come about?” Say to them, “You have\n   brought it upon yourselves.” God has power over all things. (165)\n\nTrue, the defeat sustained by the Muslims at U^ud was only half as\nheavy as that sustained a couple of years earlier by the Arabs and their\nallies at Badr, giving the Muslims a slightly higher advantage.\nNevertheless, they were defeated and had to face up to the conse-\nquences, especially that their defeat could have been avoided if they\nhad not become greedy and ignored their leader’s battle orders.\nHowever, the surah eloquently offers a most encouraging consola-\ntion for that tragic episode by saying to the Muslims:\n\n   This often happened to others before you. Look all over the world\n   and see what was the fate of the unbelievers. This is a proclamation\n   to all mankind; it is also a guide and an admonition to the God-\n   fearing. Do not, therefore, lose heart or grieve, for you shall reign\n   supreme as long as you uphold your belief. (137–39)\n\n   In the Qur’an, God has given the Muslims accounts of previous\nnations and civilizations which collapsed or were destroyed as a con-\nsequence of their stubborn rejection of God’s messages and their\nrefusal to believe. The triumph of the non-Muslim Arabs at U^ud\nwould be short-lived. Things would change, allowing Islam to pre-\nvail. However, for the Muslims to achieve supremacy and triumph,\ntwo things, not mutually exclusive, would be required: sincerity of\nintent and a proper execution of duty. Muslims are always in need of\nemphasizing the second condition, for some tend to imagine that\ngood intentions and sincerity alone are sufﬁcient to achieve success.\nWhen the Muslims’ performance is assessed, their shortcomings or\nlack of ﬁghting skills are not likely to be glossed over or overlooked.\nThey have to give their utmost, no matter how little it may be, to\nthe cause for which they are ﬁghting and then God will give them\naid and support.\n   We have seen wars between equally equipped sides that go on for\nyears or decades, and others that are brought to an end in a matter of\ndays or weeks. The worst defeat is that which comes from within, as\n\n\f                A Thematic Commentary on the Qur’an\n\na result of internal faults and weaknesses, rather than due to an\nenemy’s strength or superiority. And so it is with Muslims all\nthrough their history. Their reversals have most often been self-\ninﬂicted, being a result of disunity and internal squabbling rather\nthan the power of their enemies. Once they overcome those weak-\nnesses, they regain the initiative and move ahead. The surah stresses\nthis point very strongly when it says:\n\n   Do not, therefore, lose heart or grieve, for you shall reign supreme\n   as long as you uphold your belief. If you have sustained casualties\n   and loss, so has the other side, and that is how We alternate [victory\n   and defeat] among people so that God may distinguish the true\n   believers and choose martyrs from among you; for God does not\n   love the transgressors. (139–40)\n\n    Human history is a continual struggle between the forces of good\nand evil, beauty and repugnance, meanness and nobility. God says in\nthe Qur’an: “They will remain at odds [with one another], except\nfor those to whom your Lord has shown mercy, and that is what He\ncreated them for” (H‰d: 118–19), and “We made some of you as\nmeans to test others, to see if you would endure, and your Lord is\never aware of all” (al-Furq¥n: 20). God is no doubt capable of\ndestroying false beliefs and their adherents, but that would negate\nthe role of the believers and undermine their efforts and the favors\nthey would receive from God, who says: “Had God willed, He\ncould Himself have dispersed them, but He so ordained it that He\nmight test some of you by means of others” (Mu^ammad: 4). And so\nit has been with all the previous prophets and messengers and their\nfollowers. Every achievement made on earth on behalf of God has\ncome about as a result of human effort and endeavor. God asserts:\n\n   For, if God had not enabled people to defend themselves against\n   one another, [all] monasteries and churches and synagogues and\n\n   mosques—in [all of] which God’s name is abundantly extolled—\n   would surely have been destroyed [ere now]. (al-¤ajj: 40)\n\nSo God most wisely recalled these facts in the present surah to\nMuhammad’s followers when He was consoling them over their\nordeal at U^ud. He said:\n\n   Many a prophet went into battle supported by multitudes of devo-\n   tees, but they were never daunted by what befell them for the sake\n   of God. They neither weakened nor let up abjectly; God loves the\n   steadfast. Their only words were, “Our Lord, forgive us our sins\n   and our excesses, give us strength and victory over the unbelievers.”\n   (146–47)\n\n   The surah then continues to dress the Muslims’ wounds and raise\ntheir morale and prompt them to regain their unity and self-\nconﬁdence. It is important to recall here that the defeat at U^ud\nhad uncovered some high-caliber individuals who had displayed\nextreme courage and self-denial, and cared nothing for worldly\ngains. There were men who held to their positions even as things\nlooked very desperate. Women too entered the battleﬁeld with a\ntenacity and valor like that of the men. The battle claimed a number\nof martyrs, men and women, who sacriﬁced their own lives for the\ncause of God and His Messenger. The battle of U^ud was to remain\nengraved in the memory of Muslims, generation after generation.\nMuhammad himself was to remember U^ud constantly for the rest\nof his life, saying, “U^ud is a mountain that loves us as we love it.”\n   Martyrdom commands a place of very high regard in Islam.\nMartyrs are chosen by God Himself, as the surah conﬁrms, saying:\n“And [God] chooses martyrs from among you” (140). Those chosen\nare usually the believers who give God’s cause precedence in their\nactions over all else and who devote their whole life to the promo-\ntion, reinforcement, and defense of their faith and the Islamic way of\n\n\f               A Thematic Commentary on the Qur’an\n\nlife. We have some exceptional examples among the martyrs of\nU^ud. Take Mu|¢ab ibn ¢Umayr, for instance, who was one of the\nmost handsome and well-to-do youths of Makkah. He adopted\nIslam, left all his wealth behind, and spent the rest of his days in\npoverty; instead of silk, he was reduced to wearing clothes made of\nsheepskin. He emigrated to Madinah very early and was charged\nwith teaching the new religion to its inhabitants. He spared no effort\nto carry out that task. But there he was dying in U^ud, unable to\nafford his own burial cloth. And look at ¢Abd Allah ibn ¤aram,\nfather of a son and six daughters, who asked his son to stay and look\nafter his sisters because he did not want to remain behind when the\nMessenger went to battle. He joined the ﬁghters and was killed.\n    Martyrs were extolled in the surah as God says:\n\n   Never think that those who were slain in the cause of God are dead.\n   They are alive and well provided for by their Lord. They are pleased\n   with God’s gifts and rejoicing for those they left behind that they\n   should have nothing to fear or to regret. (169–70)\n\nGod has thereby reassured those who were martyred that their fel-\nlow Muslims will continue to uphold the true faith and support the\ncause of God and His Messenger, and that they will eventually join\nthem in Paradise.\n    During the battle of U^ud, the Muslim camp became extremely\ndangerously exposed when the archers abandoned their positions.\nIn a desperate struggle, seventy of their number were killed and\nrumor had spread that the Prophet himself was among them.\nDespite the Muslims’ defeat, the Arab tribes were not able to pro-\nceed to enter Madinah and were forced to return to Makkah. It is\nimportant, moreover, to remember here what the Muslims did\nafter their defeat at U^ud. They regrouped, tried to rise above\ntheir wounds, and made their way towards Makkah, chasing their\nArab enemies who were still contemplating a return to Madinah to\n\ncomplete their attack on it. When they realized that they were\nbeing followed by the Muslims, the Arabs hastened their pace and\nmade for Makkah. This was noted in the surah which says: “As for\nthose who after sustaining defeat responded to the call of God and\nthe Messenger, those of them who do what is right and fear God\nshall be richly rewarded” (172).\n   At this point the surah, for a while, turns back to recount the\nbehavior of the local Jews, and we note that the discussion alternates\nbetween them and the pagan Arabs. This is not surprising, since the\nMuslim community was facing both camps at the same time, as the\nsurah itself indicates:\n\n   You shall be tested in your possessions and your persons, and you\n   shall hear much that is hurtful from among those to whom the Book\n   was given before you and from the pagans. However, if you perse-\n   vere and remain God-conscious, then that will indeed be a com-\n   mendable act. (186)\n\n   The Jews of Madinah had by then overreached themselves. In\nthe Qur’an, God calls on the Muslims to spend of their wealth for\nthe cause of God, whether to support the war effort or to provide\nwelfare and help for their needy and poor people. This appeal is\nmade in another surah with such eloquence and with a powerful\nincentive. It says: “Who will grant God a generous loan? He will\nrepay him many times over. God retains and He gives abundantly\nand to Him you shall all return” (al-Baqarah: 245). Some Jews in\nMadinah, nonetheless, were saying something different. They were\nclaiming that God was in need of people’s aid, and that He was\nresorting to usury while condemning it. Surah ®l ¢Imr¥n quotes\nthem as saying: “‘God is poor, but we are rich.’ We [God] shall\nrecord what they have said” (181). Such statements were more sui-\nted to people who had neither faith in God nor consciousness of\nHim, and were symptomatic of a group who lived on corruption\n\n\f                A Thematic Commentary on the Qur’an\n\nand traded spite and envy in contravention of the teachings of the\nwise and pious among them. Earlier prophets could only exhort\ntheir people to lead other nations in piety, teach them God’s word,\nand show kindness towards them, but never look down upon them\nor manipulate and exploit them. The surah observes:\n\n   God made a covenant with those to whom the Book was given that\n   they should proclaim it to all humanity and never suppress it. But\n   they cast it behind their backs and sold it for a paltry sum. What an\n   evil bargain they had made! Never think that those who congratu-\n   late themselves and love to be praised for what they had not done,\n   will escape the scourge. A woeful chastening awaits them. (187–88)\n\n   Then the surah takes us into a different atmosphere, far removed\nfrom the past and its bittersweet reminiscences.\n   As ordinary honest human beings living in this world, experienc-\ning and observing its complexities, intricacies, and marvels, are we\nnot sometimes tempted to conclude that there is a God behind it all?\nDoes it not then lead us to thank that God and praise Him? Let us\nleave religion and interreligious strife aside for a while. Let us simply\nuse our minds and our logic and think of where we shall all end after\nwe depart from this world in which we live. Why should people\ndeny the existence of God and turn away from Him? Would it not\nbe more sensible and more conducive to acknowledge and accom-\nmodate Him in our hearts and our lives? All through human history,\nvoices have called forth and exhorted humanity to believe in God\nand be close to Him. Is it not time that people stopped to think and\ngive heed to these calls, as the surah says:\n\n   Our Lord, we have heard someone calling to the true faith saying,\n   “Believe in your Lord,” and we believed. Our Lord, forgive us our\n   sins and absolve us of our misdeeds and make us die righteous. (193)\n\nGod replies that He will overlook none of the good actions and\ndeeds of people, whether men or women, black or white. Race and\nrank do not come into this at all and only good deeds count.\n   What is it, we may ask, that some people ﬁnd so difﬁcult in believ-\ning a person who calls them to lead a righteous life based on surrender\nto God and the pleasure of His grace? What is it that drives some of us\nto oppose such individuals, stand in their way, and persecute them?\nSuch was the way in which the pagan Arabs and the bigots among the\nPeople of the Book greeted the mission of Prophet Muhammad and\nbehaved towards him and his followers. They repressed and perse-\ncuted them, and drove them out of their homes and homelands. The\nMuslims withstood all that persecution, faced up to all kinds of hard-\nship, and eventually had to emigrate from Makkah and seek refuge in\nMadinah. Their sole concern was the preservation of their faith and\nthe defense and protection of their new religion and their commu-\nnity. Accordingly, the surah reassured them:\n\n   Their Lord answered them, saying: “I shall not deny any of you,\n   man or woman, the reward of their labor... Those who emigrated,\n   were driven out of their homes, suffered persecution for My sake\n   and fought and were slain, I shall forgive them their sins and admit\n   them to gardens with rivers running thereunder.” (195)\n\n   Following this extensive coverage of the surah’s two main sub-\njects, it closes with two verses. The ﬁrst one talks about the People\nof the Book and the stance expected of them towards Prophet\nMuhammad. It says:\n\n   There are some from among the People of the Book who truly\n   believe in God, and in what was revealed to you and what had been\n   revealed to them. They humble themselves before God and do not\n   sell God’s revelations for a triﬂing price. These shall be rewarded by\n   their Lord. (199)\n\n\f               A Thematic Commentary on the Qur’an\n\nThe verse, as we can see, extends to the Jews and the Christians an\nopen invitation that is there for posterity, to heed the call of the\nProphet of Islam and accept the message he delivered on behalf of\nGod to all humankind.\n    The second verse, and the closing one in the surah, is addressed to\nthe Muslims. “Believers, persevere in patience and constancy; vie in\nsuch perseverance; strengthen each other; and fear God; that you\nmay prosper” (200). This is a directive addressed to those who\nbelieved in Muhammad and followed him to hold fast to the message\nhe delivered and with which God had honored them. They are\nexpected to show a much higher degree of steadfastness than their\npredecessors in upholding it, and to vigorously defend it, its follow-\ners, and their lands at all times. They are not to give any leeway to\ntheir enemies to overwhelm or dominate them, as witnessed over the\nlast century or so when European colonialism swept over Muslim\nlands and controlled the lives and destinies of hundreds of millions of\nMuslims for decades. It is a call addressed to Muslims everywhere and\nof every generation, and it is up to every one of us to respond to it.",
      "verse_refs": [
        {
          "type": "same_surah",
          "verse": "128"
        },
        {
          "type": "same_surah",
          "verse": "179"
        },
        {
          "type": "same_surah",
          "verse": "154"
        },
        {
          "type": "same_surah",
          "verse": "152"
        },
        {
          "type": "same_surah",
          "verse": "152"
        },
        {
          "type": "same_surah",
          "verse": "165"
        },
        {
          "type": "same_surah",
          "verse": "140"
        },
        {
          "type": "same_surah",
          "verse": "172"
        },
        {
          "type": "same_surah",
          "verse": "186"
        },
        {
          "type": "same_surah",
          "verse": "181"
        },
        {
          "type": "same_surah",
          "verse": "193"
        },
        {
          "type": "same_surah",
          "verse": "195"
        },
        {
          "type": "same_surah",
          "verse": "199"
        },
        {
          "type": "same_surah",
          "verse": "200"
        },
        {
          "type": "same_surah",
          "verse": "137-39"
        },
        {
          "type": "same_surah",
          "verse": "139-40"
        },
        {
          "type": "same_surah",
          "verse": "146-47"
        },
        {
          "type": "same_surah",
          "verse": "169-70"
        },
        {
          "type": "same_surah",
          "verse": "187-88"
        },
        {
          "type": "cross_surah",
          "surah_name": "H‰d",
          "verse": "118–19"
        },
        {
          "type": "cross_surah",
          "surah_name": "al-Furq¥n",
          "verse": "20"
        },
        {
          "type": "cross_surah",
          "surah_name": "Mu^ammad",
          "verse": "4"
        },
        {
          "type": "cross_surah",
          "surah_name": "al-Baqarah",
          "verse": "245"
        }
      ],
      "char_count": 19646
    }
  ],
  "total_sections": 4,
  "total_chars": 48301
}