{
  "id": "thematic_090",
  "surah_number": 90,
  "surah_name": "Al-Balad",
  "surah_name_transliterated": "Al-Balad",
  "surah_name_english": "The City",
  "page_start": 751,
  "page_end": 752,
  "synopsis": "the opening verse: “I swear by this city,” (1) draws attention\nto the city of Makkah, where Prophet Muhammad was born and\nlived, to which the next verse refers: “And you are a resident of this\ncity” (2).",
  "sections": [
    {
      "section_index": 0,
      "text": "the opening verse: “I swear by this city,” (1) draws attention\nto the city of Makkah, where Prophet Muhammad was born and\nlived, to which the next verse refers: “And you are a resident of this\ncity” (2). Makkah was also a city of paradox, because although it was\na sanctuary and an inviolable city, Muhammad faced the rejection\nand persecution of its people.\n    Nevertheless, the identity and history of Makkah epitomizes\nGod’s promise to Abraham and his son Ishmael, who built its cen-\ntral shrine, the Ka¢bah, and prayed to God: “Our Lord, send forth\nto them [the Arabs of Makkah] a messenger from among them-\nselves to declare to them Your revelations, teach them the Book\nand wisdom, and purify them” (al-Baqarah: 129). This would ﬁt\nwell with the interpretation that “the parent and his offspring” in\nthe third verse is a reference to Abraham, the founder of monothe-\nism, and Muhammad, a descendant of Ishmael and the seal of the\nprophets, who established the religion of monotheism ﬁrmly on\nthis earth.\n    Man was brought to this world with a heavy burden of responsi-\nbility: “We have created man in a state of turmoil” (4). God’s tea-\nchings and the laws of the Shari¢ah were revealed to help him ration-\nalize and control his desires. The surah questions the wisdom of\ndisbelief in God and His judgment: “Does man, then, think that no\none has power over him?” (5). This echoes what is said elsewhere in\nthe Qur’an: “Does man think that We shall not gather his bones\nback together again?” (al-Qiy¥mah: 3).\n\n\f               A Thematic Commentary on the Qur’an\n\n    Man even gloats in spending his wealth, saying: “‘I have squan-\ndered vast riches’” (6). What good would wealth do if one is going\nto meet one’s Lord stripped of faith and righteousness? The surah\nasks: “Does he [man] think that none can see him?” (7). Indeed,\nevery human being shall be questioned by God on how he had\nearned his wealth and how he had spent it.\n    God then goes on to remind man of the bounties He has\nbestowed upon him, saying: “Have We not given him two eyes, and\na tongue and two lips, and shown him the two routes [of right and\nwrong]?” (8–10). It was time man used those faculties God had\ngiven him to break away from blindly following the heedless\ntraditions of the forefathers, to scale the heights, submit to God\nAlmighty, and seek the path of faith and righteousness. It was a big\nstep to take. It would entail a great deal of will-power and moral\ncourage. It would mean: “The freeing of a bondsman, or the feed-\ning, on a lean day, of an orphaned relative or a needy person in\ndistress” (12–16).\n    To that the surah adds: “And to be one of those who believe and\nexhort one another to perseverance and to mercy; these shall be of\nthe right side” (17–18). These are all features of the people of\nParadise, who seek excellence in all they do. Believers are alert,\nactive, and astute people who strive to do good until the day they\ndie, after which they will be rewarded with life in Paradise, accord-\ning to their deeds.\n    Those who are bent on evil and wrongdoing shall have a differ-\nent end. “Whereas those who deny Our revelations shall be of the\nleft side, overwhelmed by ﬁre, closing in upon them” (19–20).\n    The surah alludes to the fact that earlier prophets and messengers\nwere not successful in bringing all the people of the Arabian penin-\nsula into the fold of God’s revealed religion, a task which was only\nachieved by Muhammad, the seal of the prophets, who came from\nthe heart of Arabia and founded a community that was to carry the\ntorch of faith to all corners of the globe.",
      "verse_refs": [
        {
          "type": "same_surah",
          "verse": "1"
        },
        {
          "type": "same_surah",
          "verse": "2"
        },
        {
          "type": "same_surah",
          "verse": "4"
        },
        {
          "type": "same_surah",
          "verse": "5"
        },
        {
          "type": "same_surah",
          "verse": "6"
        },
        {
          "type": "same_surah",
          "verse": "7"
        },
        {
          "type": "same_surah",
          "verse": "8-10"
        },
        {
          "type": "same_surah",
          "verse": "12-16"
        },
        {
          "type": "same_surah",
          "verse": "17-18"
        },
        {
          "type": "same_surah",
          "verse": "19-20"
        },
        {
          "type": "cross_surah",
          "surah_name": "al-Baqarah",
          "verse": "129"
        },
        {
          "type": "cross_surah",
          "surah_name": "al-Qiy¥mah",
          "verse": "3"
        }
      ],
      "char_count": 3598
    }
  ],
  "total_sections": 1,
  "total_chars": 3598
}